lcdata/__init__.py
lcdata/gcp/__init__.py
lcdata/gcp/cloudfunction_helpers.py
lcdata/gcp/logging.py
lcdata/sql/renderers/__init__.py
lcdata/utils/python/__init__.py
lc_data_libs-0.1.14.dist-info/LICENSE
lc_data_libs-0.1.14.dist-info/METADATA
lc_data_libs-0.1.14.dist-info/WHEEL
lc_data_libs-0.1.14.dist-info/top_level.txt
lc_data_libs-0.1.14.dist-info/RECORD
