Metadata-Version: 2.1
Name: lc-data-libs
Version: 0.1.14
Summary: Usefull library for lc operations
Home-page: https://bitbucket.org/luckycart/lc-data
Author: lc-data
Author-email: data@gmail.com
License: UNKNOWN
Platform: UNKNOWN
Classifier: Programming Language :: Python :: 3
Classifier: License :: OSI Approved :: MIT License
Classifier: Operating System :: OS Independent
License-File: LICENSE
Requires-Dist: google-cloud-logging (~=3.0.0)
Requires-Dist: google-cloud-dataproc (~=4.0.0)
Requires-Dist: google-cloud-pubsub (~=2.11.0)
Requires-Dist: numpy
